MANIFEST.in
setup.py
docs/HISTORY.txt
src/dolmen/__init__.py
src/dolmen.app.content.egg-info/PKG-INFO
src/dolmen.app.content.egg-info/SOURCES.txt
src/dolmen.app.content.egg-info/dependency_links.txt
src/dolmen.app.content.egg-info/namespace_packages.txt
src/dolmen.app.content.egg-info/not-zip-safe
src/dolmen.app.content.egg-info/requires.txt
src/dolmen.app.content.egg-info/top_level.txt
src/dolmen/app/__init__.py
src/dolmen/app/content/README.txt
src/dolmen/app/content/__init__.py
src/dolmen/app/content/configure.zcml
src/dolmen/app/content/ftesting.zcml
src/dolmen/app/content/indexes.py
src/dolmen/app/content/tests.py
src/dolmen/app/content/thumbnails.py